pyjamaz/__init__.py
pyjamaz/cli.py
pyjamaz-0.0.1.dist-info/LICENSE
pyjamaz-0.0.1.dist-info/METADATA
pyjamaz-0.0.1.dist-info/WHEEL
pyjamaz-0.0.1.dist-info/entry_points.txt
pyjamaz-0.0.1.dist-info/top_level.txt
pyjamaz-0.0.1.dist-info/RECORD
