Metadata-Version: 2.1
Name: pyjamaz
Version: 0.0.1
Summary: Python JAM implementation
Author-email: JAMdot Technologies <devops@jamdot.tech>
License: GNU GENERAL PUBLIC LICENSE
Project-URL: Homepage, https://github.com/JAMdotTech/pyjamaz
Classifier: Programming Language :: Python :: 3
Classifier: License :: OSI Approved :: GNU General Public License v3 (GPLv3)
Classifier: Operating System :: OS Independent
Requires-Python: >=3.8
License-File: LICENSE
Requires-Dist: setuptools~=69.0.3
Requires-Dist: click~=8.1
Provides-Extra: dev
Requires-Dist: coverage==5.3; extra == "dev"
Requires-Dist: pytest>=6.1.2; extra == "dev"
Requires-Dist: mkdocs; extra == "dev"
Requires-Dist: mkdocs-material; extra == "dev"
Requires-Dist: mkdocs-autorefs; extra == "dev"
Requires-Dist: mkdocstrings; extra == "dev"
Requires-Dist: mkdocstrings[python]; extra == "dev"
